{
  "albums": [
    {
      "id": 2,
      "name": "novo album",
      "image": "wallpapersden.com_cool-red-mountains-4k_4000x2250.jpg"
    },
    {
      "id": 3,
      "name": "fdfdf",
      "image": "a.png"
    },
    {
      "id": 4,
      "name": "fdfdfgdgfhgf hfgjhfghjghj fg jyghj",
      "image": "wallpapersden.com_cool-red-mountains-4k_4000x2250.jpg"
    },
    {
      "id": 5,
      "name": "allllbum",
      "image": "dsd.jpg"
    },
    {
      "id": 6,
      "name": "dcd",
      "image": "wallpapersden.com_cool-red-mountains-4k_4000x2250.jpg"
    }
  ],
  "songs": [
    {
      "id": 1,
      "name": "dsd",
      "number": "-",
      "times_played": 5,
      "file": "MA_37roommusic_ APartOfMyLife.wav",
      "albumId": 2
    },
    {
      "id": 2,
      "name": "dsd",
      "number": "-",
      "times_played": 0,
      "file": "MA_37roommusic_ APartOfMyLife.wav",
      "albumId": 2
    },
    {
      "id": 3,
      "name": "dsd",
      "number": "-",
      "times_played": 0,
      "file": "MA_37roommusic_ APartOfMyLife.wav",
      "albumId": 2
    },
    {
      "id": 4,
      "name": "dsd",
      "number": "-",
      "times_played": 0,
      "file": "MA_37roommusic_ APartOfMyLife.wav",
      "albumId": 2
    },
    {
      "id": 5,
      "name": "dsd",
      "number": "-",
      "times_played": 0,
      "file": "MA_37roommusic_ APartOfMyLife.wav",
      "albumId": 2
    },
    {
      "id": 6,
      "name": "dsd",
      "number": "-",
      "times_played": 0,
      "file": "MA_37roommusic_ APartOfMyLife.wav",
      "albumId": 2
    },
    {
      "id": 7,
      "name": "dsd",
      "number": "-",
      "times_played": 0,
      "file": "MA_37roommusic_ APartOfMyLife.wav",
      "albumId": 2
    },
    {
      "id": 8,
      "name": "dsd",
      "number": "-",
      "times_played": 0,
      "file": "MA_37roommusic_ APartOfMyLife.wav",
      "albumId": 2
    },
    {
      "id": 9,
      "name": "dsd",
      "number": "-",
      "times_played": 0,
      "file": "MA_37roommusic_ APartOfMyLife.wav",
      "albumId": 2
    },
    {
      "id": 10,
      "name": "dsd",
      "number": "-",
      "times_played": 0,
      "file": "MA_37roommusic_ APartOfMyLife.wav",
      "albumId": 2
    },
    {
      "id": 11,
      "name": "dsd",
      "number": "-",
      "times_played": 0,
      "file": "MA_37roommusic_ APartOfMyLife.wav",
      "albumId": 2
    },
    {
      "id": 12,
      "name": "dsd",
      "number": "-",
      "times_played": 0,
      "file": "MA_37roommusic_ APartOfMyLife.wav",
      "albumId": 2
    },
    {
      "id": 13,
      "name": "dsd",
      "number": "-",
      "times_played": 0,
      "file": "MA_37roommusic_ APartOfMyLife.wav",
      "albumId": 2
    },
    {
      "id": 14,
      "name": "dsd",
      "number": null,
      "times_played": 0,
      "file": "MA_37roommusic_ APartOfMyLife.wav",
      "albumId": 2
    },
    {
      "id": 15,
      "name": "dsd",
      "number": "-",
      "times_played": 0,
      "file": "MA_37roommusic_ APartOfMyLife.wav",
      "albumId": 2
    },
    {
      "id": 16,
      "name": "dsd",
      "number": "-",
      "times_played": 0,
      "file": "MA_37roommusic_ APartOfMyLife.wav",
      "albumId": 2
    },
    {
      "id": 17,
      "name": "teeeeste",
      "number": "2",
      "times_played": 2,
      "file": "MA_37roommusic_ APartOfMyLife.wav",
      "albumId": 2
    },
    {
      "id": 18,
      "name": "fggbdfgbdfv. d sfsd d. fdf df dfdasf",
      "number": "-",
      "times_played": 0,
      "file": "MA_37roommusic_ APartOfMyLife.wav",
      "albumId": 2
    },
    {
      "id": 19,
      "name": "nova musicanova musicanova musicanova musica",
      "number": "-",
      "times_played": 0,
      "file": "MA_Jewel_AutumnGarden_Main.wav",
      "albumId": 2
    },
    {
      "id": 20,
      "name": "dfdfd",
      "number": "-",
      "times_played": 5,
      "file": "MA_IvanLuzan_InspirationalSpeech.wav",
      "albumId": 2
    },
    {
      "id": 21,
      "name": "sooong",
      "number": "-",
      "times_played": 3,
      "file": "MA_Jewel_AutumnGarden_Main.wav",
      "albumId": 2
    },
    {
      "id": 22,
      "name": "fdfd",
      "number": null,
      "times_played": 0,
      "file": "MA_37roommusic_-APartOfMyLife.mp3",
      "albumId": 3
    },
    {
      "id": 23,
      "name": "dsdsdsfgsgfd",
      "number": null,
      "times_played": 0,
      "file": "MA_Jewel_AutumnGarden_Main.wav",
      "albumId": 3
    },
    {
      "id": 24,
      "name": "fdfddasf",
      "number": null,
      "times_played": 0,
      "file": "MA_IvanLuzan_InspirationalSpeech.wav",
      "albumId": 3
    },
    {
      "id": 25,
      "name": "fdfdsf",
      "number": null,
      "times_played": 0,
      "file": "MA_Tapetunes_MissYou.wav",
      "albumId": 3
    },
    {
      "id": 26,
      "name": "jhgfds",
      "number": "-",
      "times_played": 1,
      "file": "MA_Tapetunes_MissYou.wav",
      "albumId": 3
    }
  ],
  "worships": [
    {
      "id": 1,
      "name": "testedsds",
      "image": "dsd.jpg"
    },
    {
      "id": 2,
      "name": "fghgfhgdf hfghghjghm gjhjgfjn h jmghgjn fgjn fhg",
      "image": "wallpapersden.com_cool-red-mountains-4k_4000x2250.jpg"
    },
    {
      "id": 3,
      "name": "ffvfvcfdfcv gdvxbv",
      "image": "Screenshot 2023-12-28 at 17.53.06.png"
    }
  ],
  "moments": [
    {
      "id": 1,
      "label": "inicio",
      "songId": 17,
      "worshipId": 1,
      "song": {
        "id": 17,
        "name": "teeeeste",
        "number": 2,
        "times_played": 1,
        "file": "MA_37roommusic_ APartOfMyLife.wav",
        "albumId": 2,
        "album": {
          "id": 2,
          "name": "novo album",
          "image": "wallpapersden.com_cool-red-mountains-4k_4000x2250.jpg"
        }
      }
    },
    {
      "id": 2,
      "label": "sermaoffd",
      "songId": 19,
      "worshipId": 1
    },
    {
      "id": 3,
      "label": "fdfdf",
      "songId": 20,
      "worshipId": 1
    },
    {
      "id": 4,
      "label": "song",
      "songId": 26,
      "worshipId": 1
    }
  ],
  "history": [
    {
      "id": 11,
      "songId": 1,
      "albumId": 2
    },
    {
      "id": 13,
      "songId": 21,
      "albumId": 2
    },
    {
      "id": 14,
      "songId": 26,
      "albumId": 3
    },
    {
      "id": 15,
      "songId": 20,
      "albumId": 2
    },
    {
      "id": 16,
      "songId": 17,
      "albumId": 2
    }
  ]
}